spell4checker/__init__.py
spell4checker/spell_check.py
spell4checker-0.0.1.dist-info/METADATA
spell4checker-0.0.1.dist-info/WHEEL
spell4checker-0.0.1.dist-info/top_level.txt
spell4checker-0.0.1.dist-info/RECORD
