Metadata-Version: 2.1
Name: spell4checker
Version: 0.0.1
Author: TAWSIF AHMED
Author-email: sleeping4cat@outlook.com
